csimdjson.abi3.so
pysimdjson-7.0.2.dist-info/WHEEL
pysimdjson-7.0.2.dist-info/top_level.txt
pysimdjson-7.0.2.dist-info/RECORD
pysimdjson-7.0.2.dist-info/METADATA
pysimdjson-7.0.2.dist-info/licenses/LICENSE
simdjson/csimdjson.pyx
simdjson/util.cpp
simdjson/__init__.pyi
simdjson/__init__.py
simdjson/py.typed
simdjson/simdjson.cpp
simdjson/csimdjson.pxd
simdjson/util.h
simdjson/simdjson.h
