Metadata-Version: 2.4
Name: pysimdjson
Version: 7.0.2
Summary: Add your description here
Requires-Python: >=3.9
License-File: LICENSE
Dynamic: license-file
